baselines/__init__.py
baselines/helpers.py
baselines/plots.py
density_forest/__init__.py
density_forest/create_data.py
density_forest/decision_tree.py
density_forest/decision_tree_create.py
density_forest/decision_tree_traverse.py
density_forest/density_forest.py
density_forest/density_tree.py
density_forest/density_tree_create.py
density_forest/density_tree_traverse.py
density_forest/helpers.py
density_forest/random_forest.py
density_forest-0.5.1.dist-info/METADATA
density_forest-0.5.1.dist-info/RECORD
density_forest-0.5.1.dist-info/WHEEL
density_forest-0.5.1.dist-info/top_level.txt
helpers/__init__.py
helpers/data_augment.py
helpers/data_loader.py
helpers/helpers.py
helpers/parameter_search.py
helpers/plots.py
keras_helpers/__init__.py
keras_helpers/callbacks.py
keras_helpers/unet.py
