Metadata-Version: 2.1
Name: density-forest
Version: 0.5.1
Summary: Density Forest library for confidence estimation and novelty detection
Home-page: https://github.com/CyrilWendl/SIE-Master
Author: Cyril Wendl
Author-email: cyrilwendl@gmail.com
License: MIT
Platform: UNKNOWN
Requires-Dist: numpy
Requires-Dist: matplotlib
Requires-Dist: scipy
Requires-Dist: tqdm
Requires-Dist: Cython
Requires-Dist: scikit-image
Requires-Dist: pandas
Requires-Dist: joblib
Requires-Dist: pip
Requires-Dist: sklearn
